{"stocks":[{"name":"中际旭创","code":"300308","industry":"通信设备","price":1121.9,"amount":32709219195.06,"daily_gain":2.09,"gain_3d":-1.85,"gain_10d":-14.36,"gain_30d":2.64,"dist_abnormal":18.15,"dist_severe":35.64,"consecutive":14,"board_10d":10,"board_30d":13},{"name":"兆易创新","code":"603986","industry":"半导体","price":620.0,"amount":32272585837.0,"daily_gain":-5.24,"gain_3d":-10.77,"gain_10d":-3.27,"gain_30d":20.42,"dist_abnormal":9.23,"dist_severe":96.73,"consecutive":14,"board_10d":10,"board_30d":13},{"name":"新易盛","code":"300502","industry":"通信设备","price":510.1,"amount":22935005483.46,"daily_gain":0.63,"gain_3d":0.22,"gain_10d":-7.59,"gain_30d":8.53,"dist_abnormal":19.78,"dist_severe":42.41,"consecutive":14,"board_10d":10,"board_30d":13},{"name":"长电科技","code":"600584","industry":"半导体","price":100.99,"amount":22578698079.0,"daily_gain":6.2,"gain_3d":5.22,"gain_10d":17.31,"gain_30d":26.13,"dist_abnormal":14.78,"dist_severe":82.69,"consecutive":14,"board_10d":10,"board_30d":13},{"name":"京东方Ａ","code":"000725","industry":"光学光电子","price":7.58,"amount":21575002743.3,"daily_gain":-2.32,"gain_3d":-16.7,"gain_10d":11.96,"gain_30d":45.38,"dist_abnormal":3.3,"dist_severe":88.04,"consecutive":14,"board_10d":10,"board_30d":13},{"name":"东山精密","code":"002384","industry":"元件","price":236.87,"amount":21486739355.71,"daily_gain":5.53,"gain_3d":6.85,"gain_10d":-7.12,"gain_30d":4.7,"dist_abnormal":13.15,"dist_severe":92.88,"consecutive":14,"board_10d":10,"board_30d":13},{"name":"寒武纪","code":"688256","industry":"半导体","price":1388.0,"amount":16641769701.0,"daily_gain":1.33,"gain_3d":1.17,"gain_10d":-1.77,"gain_30d":-1.32,"dist_abnormal":18.83,"dist_severe":48.23,"consecutive":14,"board_10d":10,"board_30d":13},{"name":"澜起科技","code":"688008","industry":"半导体","price":253.2,"amount":15610414958.0,"daily_gain":-5.76,"gain_3d":-5.93,"gain_10d":-1.86,"gain_30d":-10.87,"dist_abnormal":14.07,"dist_severe":48.14,"consecutive":14,"board_10d":10,"board_30d":13},{"name":"亨通光电","code":"600487","industry":"通信设备","price":80.89,"amount":13866392537.0,"daily_gain":-4.39,"gain_3d":-13.8,"gain_10d":-30.88,"gain_30d":10.6,"dist_abnormal":6.2,"dist_severe":69.12,"consecutive":14,"board_10d":10,"board_30d":13},{"name":"中国巨石","code":"600176","industry":"玻璃玻纤","price":60.0,"amount":13141548212.0,"daily_gain":-5.97,"gain_3d":-11.53,"gain_10d":1.82,"gain_30d":52.94,"dist_abnormal":8.47,"dist_severe":98.18,"consecutive":13,"board_10d":10,"board_30d":12},{"name":"德明利","code":"001309","industry":"半导体","price":851.0,"amount":12502147620.46,"daily_gain":-8.98,"gain_3d":4.93,"gain_10d":12.71,"gain_30d":22.45,"dist_abnormal":15.07,"dist_severe":87.29,"consecutive":14,"board_10d":10,"board_30d":13},{"name":"华天科技","code":"002185","industry":"半导体","price":21.93,"amount":11999102684.88,"daily_gain":9.98,"gain_3d":8.19,"gain_10d":12.23,"gain_30d":29.4,"dist_abnormal":11.81,"dist_severe":87.77,"consecutive":14,"board_10d":10,"board_30d":13},{"name":"佰维存储","code":"688525","industry":"半导体","price":425.0,"amount":11982625727.0,"daily_gain":-6.53,"gain_3d":1.48,"gain_10d":9.12,"gain_30d":32.58,"dist_abnormal":18.52,"dist_severe":40.88,"consecutive":14,"board_10d":10,"board_30d":13},{"name":"江波龙","code":"301308","industry":"半导体","price":627.9,"amount":11770602309.87,"daily_gain":-7.91,"gain_3d":4.79,"gain_10d":5.35,"gain_30d":11.23,"dist_abnormal":15.21,"dist_severe":94.65,"consecutive":14,"board_10d":10,"board_30d":13},{"name":"北京君正","code":"300223","industry":"半导体","price":231.2,"amount":10970697107.28,"daily_gain":-8.62,"gain_3d":-1.48,"gain_10d":19.18,"gain_30d":62.91,"dist_abnormal":18.52,"dist_severe":30.82,"consecutive":13,"board_10d":10,"board_30d":12},{"name":"海光信息","code":"688041","industry":"半导体","price":342.6,"amount":10571575642.0,"daily_gain":1.06,"gain_3d":6.3,"gain_10d":8.08,"gain_30d":3.97,"dist_abnormal":13.7,"dist_severe":41.92,"consecutive":14,"board_10d":10,"board_30d":13},{"name":"北方华创","code":"002371","industry":"半导体","price":806.39,"amount":10562009151.62,"daily_gain":0.35,"gain_3d":-4.12,"gain_10d":7.99,"gain_30d":15.62,"dist_abnormal":15.88,"dist_severe":92.01,"consecutive":13,"board_10d":10,"board_30d":12},{"name":"中微公司","code":"688012","industry":"半导体","price":420.04,"amount":10350140213.0,"daily_gain":0.01,"gain_3d":2.72,"gain_10d":13.0,"gain_30d":29.06,"dist_abnormal":17.28,"dist_severe":37.0,"consecutive":14,"board_10d":10,"board_30d":13},{"name":"光迅科技","code":"002281","industry":"通信设备","price":221.67,"amount":10238875034.97,"daily_gain":6.05,"gain_3d":1.59,"gain_10d":-16.95,"gain_30d":-1.03,"dist_abnormal":18.41,"dist_severe":83.05,"consecutive":14,"board_10d":10,"board_30d":13},{"name":"天孚通信","code":"300394","industry":"通信设备","price":244.09,"amount":10210084576.08,"daily_gain":2.99,"gain_3d":-2.66,"gain_10d":-21.53,"gain_30d":-13.72,"dist_abnormal":17.34,"dist_severe":28.47,"consecutive":14,"board_10d":10,"board_30d":13},{"name":"中芯国际","code":"688981","industry":"半导体","price":145.42,"amount":10086679237.0,"daily_gain":0.99,"gain_3d":0.92,"gain_10d":2.63,"gain_30d":-6.78,"dist_abnormal":19.08,"dist_severe":47.37,"consecutive":14,"board_10d":10,"board_30d":13},{"name":"中天科技","code":"600522","industry":"通信设备","price":47.27,"amount":9218248395.0,"daily_gain":-1.58,"gain_3d":-8.36,"gain_10d":-23.42,"gain_30d":10.21,"dist_abnormal":11.64,"dist_severe":76.58,"consecutive":14,"board_10d":10,"board_30d":13},{"name":"深科技","code":"000021","industry":"消费电子","price":54.07,"amount":9214178045.21,"daily_gain":1.44,"gain_3d":-3.5,"gain_10d":18.32,"gain_30d":32.1,"dist_abnormal":16.5,"dist_severe":81.68,"consecutive":13,"board_10d":10,"board_30d":12},{"name":"紫光股份","code":"000938","industry":"IT服务Ⅱ","price":31.48,"amount":8917565681.08,"daily_gain":-5.49,"gain_3d":8.44,"gain_10d":16.98,"gain_30d":1.63,"dist_abnormal":11.56,"dist_severe":83.02,"consecutive":5,"board_10d":4,"board_30d":4},{"name":"太极实业","code":"600667","industry":"工程咨询服务Ⅱ","price":26.32,"amount":8788887339.0,"daily_gain":-3.98,"gain_3d":-8.9,"gain_10d":26.2,"gain_30d":98.27,"dist_abnormal":11.1,"dist_severe":73.8,"consecutive":8,"board_10d":8,"board_30d":10},{"name":"绿的谐波","code":"688017","industry":"自动化设备","price":465.07,"amount":8755760597.0,"daily_gain":2.44,"gain_3d":12.6,"gain_10d":22.87,"gain_30d":33.28,"dist_abnormal":7.4,"dist_severe":27.13,"consecutive":6,"board_10d":5,"board_30d":6},{"name":"立讯精密","code":"002475","industry":"消费电子","price":63.28,"amount":8712510967.18,"daily_gain":0.64,"gain_3d":3.91,"gain_10d":-8.77,"gain_30d":-15.29,"dist_abnormal":16.09,"dist_severe":91.23,"consecutive":14,"board_10d":10,"board_30d":13},{"name":"通富微电","code":"002156","industry":"半导体","price":68.21,"amount":8575725760.19,"daily_gain":3.07,"gain_3d":1.25,"gain_10d":-0.31,"gain_30d":-2.14,"dist_abnormal":18.75,"dist_severe":99.69,"consecutive":14,"board_10d":10,"board_30d":13},{"name":"香农芯创","code":"300475","industry":"其他电子Ⅱ","price":244.33,"amount":8402320010.54,"daily_gain":-7.8,"gain_3d":-6.76,"gain_10d":-13.82,"gain_30d":19.44,"dist_abnormal":13.24,"dist_severe":36.18,"consecutive":14,"board_10d":10,"board_30d":13},{"name":"埃斯顿","code":"002747","industry":"自动化设备","price":49.0,"amount":8304435303.72,"daily_gain":6.45,"gain_3d":20.39,"gain_10d":28.1,"gain_30d":71.27,"dist_abnormal":-0.39,"dist_severe":71.9,"consecutive":4,"board_10d":3,"board_30d":3},{"name":"东方财富","code":"300059","industry":"证券Ⅱ","price":20.29,"amount":8283131864.88,"daily_gain":-4.2,"gain_3d":-2.12,"gain_10d":-2.92,"gain_30d":2.11,"dist_abnormal":17.88,"dist_severe":47.08,"consecutive":13,"board_10d":10,"board_30d":12},{"name":"源杰科技","code":"688498","industry":"半导体","price":1715.04,"amount":8198050608.0,"daily_gain":4.58,"gain_3d":4.64,"gain_10d":-5.68,"gain_30d":58.19,"dist_abnormal":15.36,"dist_severe":44.32,"consecutive":13,"board_10d":10,"board_30d":12},{"name":"胜宏科技","code":"300476","industry":"元件","price":284.92,"amount":8014283920.56,"daily_gain":-2.68,"gain_3d":-6.92,"gain_10d":-15.75,"gain_30d":-25.71,"dist_abnormal":13.08,"dist_severe":34.25,"consecutive":14,"board_10d":10,"board_30d":13},{"name":"药明康德","code":"603259","industry":"医疗服务","price":118.3,"amount":7981712118.0,"daily_gain":-3.8,"gain_3d":-2.47,"gain_10d":11.28,"gain_30d":17.16,"dist_abnormal":17.53,"dist_severe":88.72,"consecutive":12,"board_10d":10,"board_30d":11},{"name":"宁德时代","code":"300750","industry":"电池","price":372.49,"amount":7796643168.18,"daily_gain":-0.54,"gain_3d":-2.58,"gain_10d":-5.1,"gain_30d":-7.54,"dist_abnormal":17.42,"dist_severe":44.9,"consecutive":14,"board_10d":10,"board_30d":13},{"name":"沪电股份","code":"002463","industry":"元件","price":129.72,"amount":7702456407.49,"daily_gain":0.69,"gain_3d":-0.61,"gain_10d":-6.34,"gain_30d":5.86,"dist_abnormal":19.39,"dist_severe":93.66,"consecutive":14,"board_10d":10,"board_30d":13},{"name":"多氟多","code":"002407","industry":"化学制品","price":45.35,"amount":7585286908.44,"daily_gain":-1.11,"gain_3d":-17.27,"gain_10d":8.49,"gain_30d":18.01,"dist_abnormal":2.73,"dist_severe":91.51,"consecutive":4,"board_10d":8,"board_30d":10},{"name":"深南电路","code":"002916","industry":"元件","price":412.1,"amount":7567814305.97,"daily_gain":-6.38,"gain_3d":-2.6,"gain_10d":-3.26,"gain_30d":3.65,"dist_abnormal":17.4,"dist_severe":96.74,"consecutive":4,"board_10d":7,"board_30d":8},{"name":"三环集团","code":"300408","industry":"元件","price":140.0,"amount":7507277160.64,"daily_gain":-1.22,"gain_3d":-5.53,"gain_10d":-3.78,"gain_30d":21.37,"dist_abnormal":14.47,"dist_severe":46.22,"consecutive":14,"board_10d":10,"board_30d":13},{"name":"华工科技","code":"000988","industry":"自动化设备","price":153.59,"amount":7401491989.13,"daily_gain":2.6,"gain_3d":-1.67,"gain_10d":-6.15,"gain_30d":-10.54,"dist_abnormal":18.33,"dist_severe":93.85,"consecutive":14,"board_10d":10,"board_30d":13},{"name":"浪潮信息","code":"000977","industry":"计算机设备","price":71.06,"amount":7359232001.4,"daily_gain":1.94,"gain_3d":11.4,"gain_10d":11.03,"gain_30d":2.69,"dist_abnormal":8.6,"dist_severe":88.97,"consecutive":3,"board_10d":5,"board_30d":5},{"name":"生益科技","code":"600183","industry":"元件","price":150.77,"amount":7317721094.0,"daily_gain":-2.27,"gain_3d":-0.78,"gain_10d":-10.19,"gain_30d":30.29,"dist_abnormal":19.22,"dist_severe":89.81,"consecutive":14,"board_10d":10,"board_30d":13},{"name":"华虹宏力","code":"688347","industry":"半导体","price":324.0,"amount":7230045983.0,"daily_gain":4.62,"gain_3d":13.88,"gain_10d":10.93,"gain_30d":50.84,"dist_abnormal":6.12,"dist_severe":39.07,"consecutive":13,"board_10d":10,"board_30d":12},{"name":"云南锗业","code":"002428","industry":"小金属","price":110.0,"amount":7121543097.18,"daily_gain":4.45,"gain_3d":2.91,"gain_10d":-1.69,"gain_30d":23.06,"dist_abnormal":17.09,"dist_severe":98.31,"consecutive":14,"board_10d":10,"board_30d":13},{"name":"芯原股份","code":"688521","industry":"半导体","price":305.26,"amount":6912123231.0,"daily_gain":1.96,"gain_3d":-1.37,"gain_10d":7.11,"gain_30d":6.63,"dist_abnormal":18.63,"dist_severe":42.89,"consecutive":13,"board_10d":10,"board_30d":12},{"name":"黄河旋风","code":"600172","industry":"通用设备","price":18.36,"amount":6860525095.0,"daily_gain":-1.02,"gain_3d":1.83,"gain_10d":8.32,"gain_30d":51.86,"dist_abnormal":18.17,"dist_severe":91.68,"consecutive":2,"board_10d":3,"board_30d":3},{"name":"永鼎股份","code":"600105","industry":"通信设备","price":49.05,"amount":6808965660.0,"daily_gain":-2.0,"gain_3d":-12.74,"gain_10d":-21.51,"gain_30d":3.95,"dist_abnormal":7.26,"dist_severe":78.49,"consecutive":14,"board_10d":10,"board_30d":13},{"name":"沪硅产业","code":"688126","industry":"半导体","price":36.28,"amount":6761959483.0,"daily_gain":4.83,"gain_3d":-3.12,"gain_10d":12.6,"gain_30d":24.89,"dist_abnormal":16.88,"dist_severe":37.4,"consecutive":10,"board_10d":9,"board_30d":11},{"name":"普冉股份","code":"688766","industry":"半导体","price":710.0,"amount":6735136780.0,"daily_gain":-6.58,"gain_3d":-9.5,"gain_10d":1.0,"gain_30d":69.1,"dist_abnormal":10.5,"dist_severe":49.0,"consecutive":13,"board_10d":10,"board_30d":12},{"name":"国瓷材料","code":"300285","industry":"电子化学品Ⅱ","price":87.55,"amount":6668108264.53,"daily_gain":-0.62,"gain_3d":-5.65,"gain_10d":-3.56,"gain_30d":71.5,"dist_abnormal":14.35,"dist_severe":46.44,"consecutive":14,"board_10d":10,"board_30d":13},{"name":"三花智控","code":"002050","industry":"家电零部件Ⅱ","price":45.51,"amount":6477016035.7,"daily_gain":-1.39,"gain_3d":1.31,"gain_10d":5.37,"gain_30d":-15.58,"dist_abnormal":18.69,"dist_severe":94.63,"consecutive":4,"board_10d":4,"board_30d":5},{"name":"TCL科技","code":"000100","industry":"光学光电子","price":5.26,"amount":6443507982.57,"daily_gain":1.35,"gain_3d":-11.15,"gain_10d":8.45,"gain_30d":20.92,"dist_abnormal":8.85,"dist_severe":91.55,"consecutive":10,"board_10d":9,"board_30d":12},{"name":"国际复材","code":"301526","industry":"玻璃玻纤","price":40.3,"amount":6405635789.04,"daily_gain":-0.89,"gain_3d":-10.82,"gain_10d":5.41,"gain_30d":87.09,"dist_abnormal":9.18,"dist_severe":94.59,"consecutive":14,"board_10d":10,"board_30d":13},{"name":"蓝思科技","code":"300433","industry":"消费电子","price":51.85,"amount":6376705991.85,"daily_gain":1.05,"gain_3d":3.2,"gain_10d":-1.93,"gain_30d":32.71,"dist_abnormal":16.8,"dist_severe":48.07,"consecutive":14,"board_10d":10,"board_30d":13},{"name":"天华新能","code":"300390","industry":"电池","price":96.26,"amount":6372531309.29,"daily_gain":5.66,"gain_3d":5.37,"gain_10d":9.85,"gain_30d":6.39,"dist_abnormal":14.63,"dist_severe":40.15,"consecutive":-1,"board_10d":5,"board_30d":6},{"name":"紫金矿业","code":"601899","industry":"工业金属","price":27.62,"amount":6197952062.0,"daily_gain":-2.33,"gain_3d":5.02,"gain_10d":0.91,"gain_30d":-10.82,"dist_abnormal":14.98,"dist_severe":99.09,"consecutive":13,"board_10d":10,"board_30d":12},{"name":"长川科技","code":"300604","industry":"半导体","price":304.33,"amount":6151253409.08,"daily_gain":0.11,"gain_3d":0.95,"gain_10d":8.92,"gain_30d":22.76,"dist_abnormal":19.05,"dist_severe":41.08,"consecutive":13,"board_10d":10,"board_30d":12},{"name":"工业富联","code":"601138","industry":"消费电子","price":63.78,"amount":6117004011.0,"daily_gain":0.3,"gain_3d":-0.37,"gain_10d":-13.93,"gain_30d":-9.27,"dist_abnormal":19.63,"dist_severe":86.07,"consecutive":14,"board_10d":10,"board_30d":13},{"name":"恒瑞医药","code":"600276","industry":"化学制药","price":55.36,"amount":5989364938.0,"daily_gain":-2.48,"gain_3d":3.5,"gain_10d":13.03,"gain_30d":12.45,"dist_abnormal":16.5,"dist_severe":86.97,"consecutive":7,"board_10d":7,"board_30d":8},{"name":"中钨高新","code":"000657","industry":"小金属","price":76.84,"amount":5875928358.17,"daily_gain":-4.5,"gain_3d":-20.62,"gain_10d":-24.87,"gain_30d":20.1,"dist_abnormal":-0.62,"dist_severe":75.13,"consecutive":14,"board_10d":10,"board_30d":13},{"name":"三安光电","code":"600703","industry":"光学光电子","price":17.78,"amount":5748411800.0,"daily_gain":2.48,"gain_3d":-6.62,"gain_10d":-10.34,"gain_30d":10.23,"dist_abnormal":13.38,"dist_severe":89.66,"consecutive":2,"board_10d":8,"board_30d":9},{"name":"阳光电源","code":"300274","industry":"光伏设备","price":127.53,"amount":5687469502.36,"daily_gain":-0.51,"gain_3d":-0.24,"gain_10d":-16.1,"gain_30d":-23.74,"dist_abnormal":19.76,"dist_severe":33.9,"consecutive":14,"board_10d":10,"board_30d":13},{"name":"中科曙光","code":"603019","industry":"计算机设备","price":93.5,"amount":5680085784.0,"daily_gain":-1.12,"gain_3d":-1.12,"gain_10d":7.4,"gain_30d":-2.68,"dist_abnormal":18.88,"dist_severe":92.6,"consecutive":9,"board_10d":8,"board_30d":8},{"name":"盛合晶微","code":"688820","industry":"半导体","price":197.59,"amount":5627450807.0,"daily_gain":5.18,"gain_3d":9.85,"gain_10d":-1.5,"gain_30d":-7.64,"dist_abnormal":10.15,"dist_severe":48.5,"consecutive":2,"board_10d":3,"board_30d":4},{"name":"雅克科技","code":"002409","industry":"半导体","price":185.82,"amount":5448809828.33,"daily_gain":-0.34,"gain_3d":-12.55,"gain_10d":18.12,"gain_30d":45.35,"dist_abnormal":7.45,"dist_severe":81.88,"consecutive":9,"board_10d":9,"board_30d":10},{"name":"长飞光纤","code":"601869","industry":"通信设备","price":429.16,"amount":5428316253.0,"daily_gain":-2.89,"gain_3d":-7.58,"gain_10d":-24.79,"gain_30d":11.17,"dist_abnormal":12.42,"dist_severe":75.21,"consecutive":13,"board_10d":10,"board_30d":12},{"name":"中信证券","code":"600030","industry":"证券Ⅱ","price":28.45,"amount":5421569064.0,"daily_gain":-2.67,"gain_3d":-0.59,"gain_10d":0.46,"gain_30d":10.36,"dist_abnormal":19.41,"dist_severe":99.54,"consecutive":11,"board_10d":10,"board_30d":10},{"name":"巨人网络","code":"002558","industry":"游戏Ⅱ","price":29.09,"amount":5375007209.85,"daily_gain":6.01,"gain_3d":4.98,"gain_10d":15.48,"gain_30d":10.57,"dist_abnormal":15.02,"dist_severe":84.52,"consecutive":-1,"board_10d":0,"board_30d":0},{"name":"C华润","code":"001248","industry":"电力","price":18.51,"amount":5353393357.95,"daily_gain":0.76,"gain_3d":-22.71,"gain_10d":-22.71,"gain_30d":-22.71,"dist_abnormal":-2.71,"dist_severe":77.29,"consecutive":4,"board_10d":3,"board_30d":3},{"name":"江海股份","code":"002484","industry":"元件","price":88.53,"amount":5262315726.48,"daily_gain":-8.17,"gain_3d":-10.27,"gain_10d":-6.32,"gain_30d":43.6,"dist_abnormal":9.73,"dist_severe":93.68,"consecutive":-1,"board_10d":3,"board_30d":4},{"name":"金安国纪","code":"002636","industry":"元件","price":100.03,"amount":5223305855.02,"daily_gain":3.35,"gain_3d":-10.35,"gain_10d":-7.93,"gain_30d":119.92,"dist_abnormal":9.65,"dist_severe":92.07,"consecutive":3,"board_10d":2,"board_30d":2},{"name":"士兰微","code":"600460","industry":"半导体","price":47.29,"amount":5126073686.0,"daily_gain":1.44,"gain_3d":-6.36,"gain_10d":0.53,"gain_30d":38.32,"dist_abnormal":13.64,"dist_severe":99.47,"consecutive":13,"board_10d":10,"board_30d":12},{"name":"大族激光","code":"002008","industry":"自动化设备","price":130.35,"amount":5052307261.62,"daily_gain":-0.47,"gain_3d":4.27,"gain_10d":-10.17,"gain_30d":-8.35,"dist_abnormal":15.73,"dist_severe":89.83,"consecutive":14,"board_10d":10,"board_30d":13},{"name":"中国长城","code":"000066","industry":"计算机设备","price":18.58,"amount":5030611133.93,"daily_gain":-1.28,"gain_3d":7.46,"gain_10d":4.56,"gain_30d":-9.72,"dist_abnormal":12.54,"dist_severe":95.44,"consecutive":-1,"board_10d":4,"board_30d":5},{"name":"长光华芯","code":"688048","industry":"半导体","price":411.0,"amount":5019183096.0,"daily_gain":-3.41,"gain_3d":-4.2,"gain_10d":4.83,"gain_30d":9.4,"dist_abnormal":15.8,"dist_severe":45.17,"consecutive":2,"board_10d":4,"board_30d":5},{"name":"昆仑万维","code":"300418","industry":"数字媒体","price":44.61,"amount":4997368036.48,"daily_gain":3.62,"gain_3d":-2.06,"gain_10d":6.59,"gain_30d":-7.35,"dist_abnormal":17.94,"dist_severe":43.41,"consecutive":-1,"board_10d":2,"board_30d":3},{"name":"方正科技","code":"600601","industry":"元件","price":14.7,"amount":4969398752.0,"daily_gain":-1.93,"gain_3d":-1.47,"gain_10d":9.46,"gain_30d":12.99,"dist_abnormal":18.53,"dist_severe":90.54,"consecutive":4,"board_10d":3,"board_30d":4},{"name":"昊志机电","code":"300503","industry":"通用设备","price":98.48,"amount":4968904702.46,"daily_gain":-10.31,"gain_3d":3.79,"gain_10d":21.54,"gain_30d":11.91,"dist_abnormal":16.21,"dist_severe":28.46,"consecutive":3,"board_10d":2,"board_30d":2},{"name":"瑞芯微","code":"603893","industry":"半导体","price":190.71,"amount":4967289993.0,"daily_gain":8.28,"gain_3d":7.53,"gain_10d":5.86,"gain_30d":-1.42,"dist_abnormal":12.47,"dist_severe":94.14,"consecutive":-1,"board_10d":0,"board_30d":0},{"name":"风华高科","code":"000636","industry":"元件","price":61.26,"amount":4937302493.01,"daily_gain":4.73,"gain_3d":-8.53,"gain_10d":-12.77,"gain_30d":48.16,"dist_abnormal":11.47,"dist_severe":87.23,"consecutive":5,"board_10d":9,"board_30d":12},{"name":"华丰科技","code":"688629","industry":"军工电子Ⅱ","price":199.4,"amount":4887679587.0,"daily_gain":-0.92,"gain_3d":11.15,"gain_10d":38.3,"gain_30d":29.55,"dist_abnormal":8.85,"dist_severe":11.7,"consecutive":2,"board_10d":4,"board_30d":4},{"name":"盛科通信-U","code":"688702","industry":"半导体","price":382.0,"amount":4822291769.0,"daily_gain":7.0,"gain_3d":8.2,"gain_10d":24.01,"gain_30d":20.47,"dist_abnormal":11.8,"dist_severe":25.99,"consecutive":-1,"board_10d":0,"board_30d":0},{"name":"兴森科技","code":"002436","industry":"元件","price":42.23,"amount":4792751638.98,"daily_gain":-6.76,"gain_3d":-7.0,"gain_10d":-12.93,"gain_30d":10.87,"dist_abnormal":13.0,"dist_severe":87.07,"consecutive":14,"board_10d":10,"board_30d":13},{"name":"星网锐捷","code":"002396","industry":"通信设备","price":26.45,"amount":4791099727.82,"daily_gain":2.76,"gain_3d":24.35,"gain_10d":38.55,"gain_30d":10.67,"dist_abnormal":-4.35,"dist_severe":61.45,"consecutive":-1,"board_10d":0,"board_30d":0},{"name":"麦格米特","code":"002851","industry":"其他电源设备Ⅱ","price":149.55,"amount":4767687693.95,"daily_gain":-1.35,"gain_3d":1.76,"gain_10d":-13.58,"gain_30d":12.99,"dist_abnormal":18.24,"dist_severe":86.42,"consecutive":-1,"board_10d":6,"board_30d":9},{"name":"万华化学","code":"600309","industry":"化学制品","price":71.05,"amount":4730950894.0,"daily_gain":0.04,"gain_3d":3.57,"gain_10d":-2.4,"gain_30d":-6.02,"dist_abnormal":16.43,"dist_severe":97.6,"consecutive":-1,"board_10d":0,"board_30d":0},{"name":"万通发展","code":"600246","industry":"房地产开发","price":18.6,"amount":4641981027.0,"daily_gain":9.99,"gain_3d":13.41,"gain_10d":6.96,"gain_30d":20.0,"dist_abnormal":6.59,"dist_severe":93.04,"consecutive":-1,"board_10d":0,"board_30d":0},{"name":"华海清科","code":"688120","industry":"半导体","price":276.0,"amount":4592712666.0,"daily_gain":2.6,"gain_3d":-1.78,"gain_10d":19.48,"gain_30d":31.16,"dist_abnormal":18.22,"dist_severe":30.52,"consecutive":-1,"board_10d":4,"board_30d":4},{"name":"昊华科技","code":"600378","industry":"化学制品","price":65.57,"amount":4577275350.0,"daily_gain":-4.15,"gain_3d":-20.2,"gain_10d":-1.16,"gain_30d":85.81,"dist_abnormal":-0.2,"dist_severe":98.84,"consecutive":7,"board_10d":7,"board_30d":9},{"name":"有研新材","code":"600206","industry":"半导体","price":55.98,"amount":4559045958.0,"daily_gain":10.0,"gain_3d":-3.17,"gain_10d":15.78,"gain_30d":84.85,"dist_abnormal":16.83,"dist_severe":84.22,"consecutive":11,"board_10d":10,"board_30d":11},{"name":"江丰电子","code":"300666","industry":"半导体","price":329.0,"amount":4551551344.86,"daily_gain":0.65,"gain_3d":-3.93,"gain_10d":12.35,"gain_30d":58.18,"dist_abnormal":16.07,"dist_severe":37.65,"consecutive":14,"board_10d":10,"board_30d":13},{"name":"甬矽电子","code":"688362","industry":"半导体","price":102.54,"amount":4443091834.0,"daily_gain":6.89,"gain_3d":10.27,"gain_10d":48.65,"gain_30d":51.78,"dist_abnormal":9.73,"dist_severe":1.35,"consecutive":-1,"board_10d":0,"board_30d":0},{"name":"铜冠铜箔","code":"301217","industry":"电池","price":144.82,"amount":4438011882.67,"daily_gain":0.45,"gain_3d":-8.3,"gain_10d":-15.71,"gain_30d":51.36,"dist_abnormal":11.7,"dist_severe":84.29,"consecutive":3,"board_10d":9,"board_30d":12},{"name":"中船特气","code":"688146","industry":"半导体","price":315.99,"amount":4411156961.0,"daily_gain":4.36,"gain_3d":-13.43,"gain_10d":-6.98,"gain_30d":123.5,"dist_abnormal":6.57,"dist_severe":43.02,"consecutive":-1,"board_10d":4,"board_30d":5},{"name":"领益智造","code":"002600","industry":"消费电子","price":15.93,"amount":4305429102.8,"daily_gain":-1.85,"gain_3d":-7.28,"gain_10d":-0.75,"gain_30d":-0.99,"dist_abnormal":12.72,"dist_severe":99.25,"consecutive":5,"board_10d":8,"board_30d":9},{"name":"诺德股份","code":"600110","industry":"电池","price":15.23,"amount":4304884471.0,"daily_gain":5.84,"gain_3d":4.82,"gain_10d":-1.36,"gain_30d":51.09,"dist_abnormal":15.18,"dist_severe":98.64,"consecutive":-1,"board_10d":0,"board_30d":1},{"name":"南大光电","code":"300346","industry":"电子化学品Ⅱ","price":77.3,"amount":4266544772.49,"daily_gain":-0.57,"gain_3d":-12.92,"gain_10d":8.22,"gain_30d":26.72,"dist_abnormal":7.08,"dist_severe":41.78,"consecutive":11,"board_10d":10,"board_30d":10},{"name":"信维通信","code":"300136","industry":"消费电子","price":93.4,"amount":4264542652.32,"daily_gain":-0.29,"gain_3d":-7.53,"gain_10d":-2.18,"gain_30d":-21.27,"dist_abnormal":12.47,"dist_severe":47.82,"consecutive":14,"board_10d":10,"board_30d":13},{"name":"大唐发电","code":"601991","industry":"电力","price":7.0,"amount":4233821124.0,"daily_gain":-5.28,"gain_3d":-4.5,"gain_10d":-16.07,"gain_30d":-5.41,"dist_abnormal":15.5,"dist_severe":83.93,"consecutive":-1,"board_10d":2,"board_30d":5},{"name":"东岳硅材","code":"300821","industry":"化学制品","price":23.3,"amount":4222020017.14,"daily_gain":5.81,"gain_3d":8.73,"gain_10d":22.83,"gain_30d":55.54,"dist_abnormal":11.27,"dist_severe":27.17,"consecutive":-1,"board_10d":0,"board_30d":0}],"indices":{"sh000001":{"latest_value":3990.24,"daily_gain":-1.26,"month_gain":-2.54,"week_gain":-1.32},"sz399001":{"latest_value":15225.11,"daily_gain":-1.24,"month_gain":-6.05,"week_gain":-2.39},"sz399006":{"latest_value":3911.91,"daily_gain":-0.94,"month_gain":-9.92,"week_gain":-2.69},"sh000688":{"latest_value":2001.59,"daily_gain":0.28,"month_gain":-9.34,"week_gain":1.32},"sz399005":{"latest_value":9337.22,"daily_gain":-0.56,"month_gain":-3.64,"week_gain":-1.45},"sh000300":{"latest_value":4792.26,"daily_gain":-1.03,"month_gain":-3.76,"week_gain":-1.03}},"meta":{"date":"2026-07-07","generate_time":"2026-07-07 19:31:14","total":100},"date":"2026-07-07"}